cecily/__init__.py
cecily-0.1.1.dist-info/WHEEL
cecily-0.1.1.dist-info/METADATA
cecily-0.1.1.dist-info/RECORD
