Metadata-Version: 2.1
Name: cecily
Version: 0.1.1
Summary: Minimalistic task queue using just the stdlib
License: MIT
Author: Nick Yu
Author-email: nickyu42@gmail.com
Requires-Python: >=3.10,<4.0
Classifier: License :: OSI Approved :: MIT License
Classifier: Programming Language :: Python :: 3
Classifier: Programming Language :: Python :: 3.10
